ghosty/__init__.py
ghosty/brillouin.py
ghosty/ghost_communication.py
ghosty/timing_logger.py
ghosty-0.1.2.dist-info/METADATA
ghosty-0.1.2.dist-info/WHEEL
ghosty-0.1.2.dist-info/licenses/LICENSE
ghosty-0.1.2.dist-info/RECORD
