Metadata-Version: 2.4
Name: ghosty
Version: 0.1.2
Summary: Wrapper for the Table Stable Ltd. Ghost Software
Project-URL: Homepage, https://github.com/timm-landes/ghosty
Project-URL: Issues, https://github.com/timm-landes/ghosty/issues
Author-email: Timm Landes <timm.landes@hot.uni-hannover.de>, Dag Heinemann <dag.heinemann@hot.uni-hannover.com>
License: MIT
License-File: LICENSE
Classifier: Operating System :: Microsoft :: Windows
Classifier: Programming Language :: Python :: 3
Requires-Python: <=3.12.9,>=3.6
Requires-Dist: asyncio>=3.4.3
Requires-Dist: loguru>=0.7.0
Requires-Dist: telnetlib3>=2.0.0
